megakeep/__init__.py
megakeep/megakeep.py
megakeep/parser.py
megakeep/user.py
megakeep-1.1.2.dist-info/METADATA
megakeep-1.1.2.dist-info/WHEEL
megakeep-1.1.2.dist-info/RECORD
