Metadata-Version: 2.1
Name: megakeep
Version: 1.1.2
Summary: Simple CLI to "touch" Mega accounts and avoid getting it closed due to inactivity.
Author: neriat
Requires-Python: >=3.10,<4.0
Classifier: Programming Language :: Python :: 3
Classifier: Programming Language :: Python :: 3.10
Classifier: Programming Language :: Python :: 3.11
Classifier: Programming Language :: Python :: 3.12
Requires-Dist: click (==8.0.1)
Requires-Dist: mega-py (>=1.0.8,<1.1.0)
Requires-Dist: tqdm (==4.62.2)
